[
    {
        "term": "done",
        "definition": null,
        "context": "\"generic\"",
        "term_plural": "",
        "reference": "",
        "comment": ""
    },
    {
        "term": "no_data",
        "definition": null,
        "context": "\"generic\".\"errors\"",
        "term_plural": "",
        "reference": "",
        "comment": ""
    },
    {
        "term": "unknown",
        "definition": null,
        "context": "\"generic\".\"errors\"",
        "term_plural": "",
        "reference": "",
        "comment": ""
    },
    {
        "term": "add",
        "definition": null,
        "context": "\"generic\".\"action\"",
        "term_plural": "",
        "reference": "",
        "comment": ""
    },
    {
        "term": "delete",
        "definition": null,
        "context": "\"generic\".\"action\"",
        "term_plural": "",
        "reference": "",
        "comment": ""
    },
    {
        "term": "edit",
        "definition": null,
        "context": "\"generic\".\"action\"",
        "term_plural": "",
        "reference": "",
        "comment": ""
    },
    {
        "term": "ok",
        "definition": null,
        "context": "\"generic\".\"action\"",
        "term_plural": "",
        "reference": "",
        "comment": ""
    },
    {
        "term": "cancel",
        "definition": null,
        "context": "\"generic\".\"action\"",
        "term_plural": "",
        "reference": "",
        "comment": ""
    },
    {
        "term": "profile",
        "definition": null,
        "context": "\"profile\"",
        "term_plural": "",
        "reference": "",
        "comment": ""
    },
    {
        "term": "favorites",
        "definition": null,
        "context": "\"profile\"",
        "term_plural": "",
        "reference": "",
        "comment": ""
    },
    {
        "term": "see_more",
        "definition": null,
        "context": "\"profile\"",
        "term_plural": "",
        "reference": "",
        "comment": ""
    },
    {
        "term": "user_id",
        "definition": null,
        "context": "\"profile\"",
        "term_plural": "",
        "reference": "",
        "comment": ""
    },
    {
        "term": "level",
        "definition": null,
        "context": "\"profile\"",
        "term_plural": "",
        "reference": "",
        "comment": ""
    },
    {
        "term": "favorites_count",
        "definition": null,
        "context": "\"profile\"",
        "term_plural": "",
        "reference": "",
        "comment": ""
    },
    {
        "term": "comments_count",
        "definition": null,
        "context": "\"profile\"",
        "term_plural": "",
        "reference": "",
        "comment": ""
    },
    {
        "term": "username",
        "definition": null,
        "context": "\"login\".\"form\"",
        "term_plural": "",
        "reference": "",
        "comment": ""
    },
    {
        "term": "password",
        "definition": null,
        "context": "\"login\".\"form\"",
        "term_plural": "",
        "reference": "",
        "comment": ""
    },
    {
        "term": "login",
        "definition": null,
        "context": "\"login\".\"form\"",
        "term_plural": "",
        "reference": "",
        "comment": ""
    },
    {
        "term": "greeting",
        "definition": null,
        "context": "\"login\".\"form\"",
        "term_plural": "",
        "reference": "",
        "comment": ""
    },
    {
        "term": "cancel",
        "definition": null,
        "context": "\"login\".\"form\"",
        "term_plural": "",
        "reference": "",
        "comment": ""
    },
    {
        "term": "open_web_browser",
        "definition": null,
        "context": "\"login\".\"form\"",
        "term_plural": "",
        "reference": "",
        "comment": ""
    },
    {
        "term": "api_key_instruction",
        "definition": null,
        "context": "\"login\".\"form\"",
        "term_plural": "",
        "reference": "",
        "comment": ""
    },
    {
        "term": "invalidUsernameOrPassword",
        "definition": null,
        "context": "\"login\".\"errors\"",
        "term_plural": "",
        "reference": "",
        "comment": ""
    },
    {
        "term": "missingUsername",
        "definition": null,
        "context": "\"login\".\"errors\"",
        "term_plural": "",
        "reference": "",
        "comment": ""
    },
    {
        "term": "missingPassword",
        "definition": null,
        "context": "\"login\".\"errors\"",
        "term_plural": "",
        "reference": "",
        "comment": ""
    },
    {
        "term": "notice",
        "definition": null,
        "context": "\"login\"",
        "term_plural": "",
        "reference": "",
        "comment": ""
    },
    {
        "term": "unavailable",
        "definition": null,
        "context": "\"network\"",
        "term_plural": "",
        "reference": "",
        "comment": ""
    },
    {
        "term": "more",
        "definition": null,
        "context": "\"tag\".\"related\"",
        "term_plural": "",
        "reference": "",
        "comment": ""
    },
    {
        "term": "related",
        "definition": null,
        "context": "\"tag\".\"related\"",
        "term_plural": "",
        "reference": "",
        "comment": ""
    },
    {
        "term": "add_to_current_search",
        "definition": null,
        "context": "\"tag\".\"related\"",
        "term_plural": "",
        "reference": "",
        "comment": ""
    },
    {
        "term": "open_wiki",
        "definition": null,
        "context": "\"tag\".\"related\"",
        "term_plural": "",
        "reference": "",
        "comment": ""
    },
    {
        "term": "new",
        "definition": null,
        "context": "\"tag\".\"explore\"",
        "term_plural": "",
        "reference": "",
        "comment": ""
    },
    {
        "term": "popular",
        "definition": null,
        "context": "\"tag\".\"explore\"",
        "term_plural": "",
        "reference": "",
        "comment": ""
    },
    {
        "term": "view",
        "definition": null,
        "context": "\"post\".\"detail\"",
        "term_plural": "",
        "reference": "",
        "comment": ""
    },
    {
        "term": "interval",
        "definition": null,
        "context": "\"post\".\"detail\".\"slide_show\"",
        "term_plural": "",
        "reference": "",
        "comment": ""
    },
    {
        "term": "skip_anim",
        "definition": null,
        "context": "\"post\".\"detail\".\"slide_show\"",
        "term_plural": "",
        "reference": "",
        "comment": ""
    },
    {
        "term": "ok",
        "definition": null,
        "context": "\"post\".\"detail\".\"slide_show\"",
        "term_plural": "",
        "reference": "",
        "comment": ""
    },
    {
        "term": "cancel",
        "definition": null,
        "context": "\"post\".\"detail\".\"slide_show\"",
        "term_plural": "",
        "reference": "",
        "comment": ""
    },
    {
        "term": "view_in_browser",
        "definition": null,
        "context": "\"post\".\"detail\"",
        "term_plural": "",
        "reference": "",
        "comment": ""
    },
    {
        "term": "has_parent_notice",
        "definition": null,
        "context": "\"post\".\"detail\"",
        "term_plural": "",
        "reference": "",
        "comment": ""
    },
    {
        "term": "has_children_notice",
        "definition": null,
        "context": "\"post\".\"detail\"",
        "term_plural": "",
        "reference": "",
        "comment": ""
    },
    {
        "term": "file_details",
        "definition": null,
        "context": "\"post\".\"detail\"",
        "term_plural": "",
        "reference": "",
        "comment": ""
    },
    {
        "term": "size",
        "definition": null,
        "context": "\"post\".\"detail\"",
        "term_plural": "",
        "reference": "",
        "comment": ""
    },
    {
        "term": "resolution",
        "definition": null,
        "context": "\"post\".\"detail\"",
        "term_plural": "",
        "reference": "",
        "comment": ""
    },
    {
        "term": "rating",
        "definition": null,
        "context": "\"post\".\"detail\"",
        "term_plural": "",
        "reference": "",
        "comment": ""
    },
    {
        "term": "file_format",
        "definition": null,
        "context": "\"post\".\"detail\"",
        "term_plural": "",
        "reference": "",
        "comment": ""
    },
    {
        "term": "source",
        "definition": null,
        "context": "\"post\".\"detail\".\"share\"",
        "term_plural": "",
        "reference": "",
        "comment": ""
    },
    {
        "term": "booru",
        "definition": null,
        "context": "\"post\".\"detail\".\"share\"",
        "term_plural": "",
        "reference": "",
        "comment": ""
    },
    {
        "term": "image",
        "definition": null,
        "context": "\"post\".\"detail\".\"share\"",
        "term_plural": "",
        "reference": "",
        "comment": ""
    },
    {
        "term": "copied",
        "definition": null,
        "context": "\"post\".\"detail\"",
        "term_plural": "",
        "reference": "",
        "comment": ""
    },
    {
        "term": "show_original",
        "definition": null,
        "context": "\"post\".\"detail\"",
        "term_plural": "",
        "reference": "",
        "comment": ""
    },
    {
        "term": "show_translated",
        "definition": null,
        "context": "\"post\".\"detail\"",
        "term_plural": "",
        "reference": "",
        "comment": ""
    },
    {
        "term": "login_required_notice",
        "definition": null,
        "context": "\"post\".\"detail\"",
        "term_plural": "",
        "reference": "",
        "comment": ""
    },
    {
        "term": "open_wiki",
        "definition": null,
        "context": "\"post\".\"detail\"",
        "term_plural": "",
        "reference": "",
        "comment": ""
    },
    {
        "term": "add_to_blacklist",
        "definition": null,
        "context": "\"post\".\"detail\"",
        "term_plural": "",
        "reference": "",
        "comment": ""
    },
    {
        "term": "add_to_favorites",
        "definition": null,
        "context": "\"post\".\"detail\"",
        "term_plural": "",
        "reference": "",
        "comment": ""
    },
    {
        "term": "copy_and_open_saved_search",
        "definition": null,
        "context": "\"post\".\"detail\"",
        "term_plural": "",
        "reference": "",
        "comment": ""
    },
    {
        "term": "score",
        "definition": {
            "other": ""
        },
        "context": "\"post\".\"detail\"",
        "term_plural": "score",
        "reference": "",
        "comment": ""
    },
    {
        "term": "children_of",
        "definition": null,
        "context": "\"post\".\"parent_child\"",
        "term_plural": "",
        "reference": "",
        "comment": ""
    },
    {
        "term": "preview",
        "definition": null,
        "context": "\"post\".\"action\"",
        "term_plural": "",
        "reference": "",
        "comment": ""
    },
    {
        "term": "view_comments",
        "definition": null,
        "context": "\"post\".\"action\"",
        "term_plural": "",
        "reference": "",
        "comment": ""
    },
    {
        "term": "add_to_favorite_group",
        "definition": null,
        "context": "\"post\".\"action\"",
        "term_plural": "",
        "reference": "",
        "comment": ""
    },
    {
        "term": "select",
        "definition": null,
        "context": "\"post\".\"action\"",
        "term_plural": "",
        "reference": "",
        "comment": ""
    },
    {
        "term": "view_original",
        "definition": null,
        "context": "\"post\".\"image_fullview\"",
        "term_plural": "",
        "reference": "",
        "comment": ""
    },
    {
        "term": "view_resized",
        "definition": null,
        "context": "\"post\".\"image_fullview\"",
        "term_plural": "",
        "reference": "",
        "comment": ""
    },
    {
        "term": "comments",
        "definition": null,
        "context": "\"comment\"",
        "term_plural": "",
        "reference": "",
        "comment": ""
    },
    {
        "term": "hint",
        "definition": null,
        "context": "\"comment\".\"create\"",
        "term_plural": "",
        "reference": "",
        "comment": ""
    },
    {
        "term": "loading",
        "definition": null,
        "context": "\"comment\".\"create\"",
        "term_plural": "",
        "reference": "",
        "comment": ""
    },
    {
        "term": "error",
        "definition": null,
        "context": "\"comment\".\"create\"",
        "term_plural": "",
        "reference": "",
        "comment": ""
    },
    {
        "term": "edit",
        "definition": null,
        "context": "\"comment\".\"list\"",
        "term_plural": "",
        "reference": "",
        "comment": ""
    },
    {
        "term": "reply",
        "definition": null,
        "context": "\"comment\".\"list\"",
        "term_plural": "",
        "reference": "",
        "comment": ""
    },
    {
        "term": "reply_to",
        "definition": null,
        "context": "\"comment\".\"list\"",
        "term_plural": "",
        "reference": "",
        "comment": ""
    },
    {
        "term": "delete",
        "definition": null,
        "context": "\"comment\".\"list\"",
        "term_plural": "",
        "reference": "",
        "comment": ""
    },
    {
        "term": "noComments",
        "definition": null,
        "context": "\"comment\".\"list\"",
        "term_plural": "",
        "reference": "",
        "comment": ""
    },
    {
        "term": "last_updated",
        "definition": null,
        "context": "\"comment\".\"list\"",
        "term_plural": "",
        "reference": "",
        "comment": ""
    },
    {
        "term": "send",
        "definition": null,
        "context": "\"comment\".\"list\"",
        "term_plural": "",
        "reference": "",
        "comment": ""
    },
    {
        "term": "counter",
        "definition": {
            "other": ""
        },
        "context": "\"comment\"",
        "term_plural": "counter",
        "reference": "",
        "comment": ""
    },
    {
        "term": "latest",
        "definition": null,
        "context": "\"explore\"",
        "term_plural": "",
        "reference": "",
        "comment": ""
    },
    {
        "term": "popular",
        "definition": null,
        "context": "\"explore\"",
        "term_plural": "",
        "reference": "",
        "comment": ""
    },
    {
        "term": "curated",
        "definition": null,
        "context": "\"explore\"",
        "term_plural": "",
        "reference": "",
        "comment": ""
    },
    {
        "term": "hot",
        "definition": null,
        "context": "\"explore\"",
        "term_plural": "",
        "reference": "",
        "comment": ""
    },
    {
        "term": "most_viewed",
        "definition": null,
        "context": "\"explore\"",
        "term_plural": "",
        "reference": "",
        "comment": ""
    },
    {
        "term": "see_more",
        "definition": null,
        "context": "\"explore\"",
        "term_plural": "",
        "reference": "",
        "comment": ""
    },
    {
        "term": "generic",
        "definition": null,
        "context": "\"search\".\"errors\"",
        "term_plural": "",
        "reference": "",
        "comment": ""
    },
    {
        "term": "tag_limit",
        "definition": null,
        "context": "\"search\".\"errors\"",
        "term_plural": "",
        "reference": "",
        "comment": ""
    },
    {
        "term": "database_timeout",
        "definition": null,
        "context": "\"search\".\"errors\"",
        "term_plural": "",
        "reference": "",
        "comment": ""
    },
    {
        "term": "rate_limited",
        "definition": null,
        "context": "\"search\".\"errors\"",
        "term_plural": "",
        "reference": "",
        "comment": ""
    },
    {
        "term": "pagination_limit",
        "definition": null,
        "context": "\"search\".\"errors\"",
        "term_plural": "",
        "reference": "",
        "comment": ""
    },
    {
        "term": "max_capacity",
        "definition": null,
        "context": "\"search\".\"errors\"",
        "term_plural": "",
        "reference": "",
        "comment": ""
    },
    {
        "term": "down",
        "definition": null,
        "context": "\"search\".\"errors\"",
        "term_plural": "",
        "reference": "",
        "comment": ""
    },
    {
        "term": "access_denied",
        "definition": null,
        "context": "\"search\".\"errors\"",
        "term_plural": "",
        "reference": "",
        "comment": ""
    },
    {
        "term": "forbidden",
        "definition": null,
        "context": "\"search\".\"errors\"",
        "term_plural": "",
        "reference": "",
        "comment": ""
    },
    {
        "term": "unknown",
        "definition": null,
        "context": "\"search\".\"errors\"",
        "term_plural": "",
        "reference": "",
        "comment": ""
    },
    {
        "term": "hint",
        "definition": null,
        "context": "\"search\"",
        "term_plural": "",
        "reference": "",
        "comment": ""
    },
    {
        "term": "no_result",
        "definition": null,
        "context": "\"search\"",
        "term_plural": "",
        "reference": "",
        "comment": ""
    },
    {
        "term": "empty",
        "definition": null,
        "context": "\"search\"",
        "term_plural": "",
        "reference": "",
        "comment": ""
    },
    {
        "term": "search_options",
        "definition": null,
        "context": "\"search\"",
        "term_plural": "",
        "reference": "",
        "comment": ""
    },
    {
        "term": "metatags_notice",
        "definition": null,
        "context": "\"search\"",
        "term_plural": "",
        "reference": "",
        "comment": ""
    },
    {
        "term": "history",
        "definition": null,
        "context": "\"search\".\"history\"",
        "term_plural": "",
        "reference": "",
        "comment": ""
    },
    {
        "term": "clear",
        "definition": null,
        "context": "\"search\".\"history\"",
        "term_plural": "",
        "reference": "",
        "comment": ""
    },
    {
        "term": "recent",
        "definition": null,
        "context": "\"search\".\"history\"",
        "term_plural": "",
        "reference": "",
        "comment": ""
    },
    {
        "term": "trending",
        "definition": null,
        "context": "\"search\"",
        "term_plural": "",
        "reference": "",
        "comment": ""
    },
    {
        "term": "remove_all_selected",
        "definition": null,
        "context": "\"search\"",
        "term_plural": "",
        "reference": "",
        "comment": ""
    },
    {
        "term": "pool",
        "definition": null,
        "context": "\"pool\"",
        "term_plural": "",
        "reference": "",
        "comment": ""
    },
    {
        "term": "pool_gallery",
        "definition": null,
        "context": "\"pool\"",
        "term_plural": "",
        "reference": "",
        "comment": ""
    },
    {
        "term": "mature_banned_content",
        "definition": null,
        "context": "\"pool\"",
        "term_plural": "",
        "reference": "",
        "comment": ""
    },
    {
        "term": "recent",
        "definition": null,
        "context": "\"pool\".\"order\"",
        "term_plural": "",
        "reference": "",
        "comment": ""
    },
    {
        "term": "new",
        "definition": null,
        "context": "\"pool\".\"order\"",
        "term_plural": "",
        "reference": "",
        "comment": ""
    },
    {
        "term": "post_count",
        "definition": null,
        "context": "\"pool\".\"order\"",
        "term_plural": "",
        "reference": "",
        "comment": ""
    },
    {
        "term": "name",
        "definition": null,
        "context": "\"pool\".\"order\"",
        "term_plural": "",
        "reference": "",
        "comment": ""
    },
    {
        "term": "series",
        "definition": null,
        "context": "\"pool\".\"category\"",
        "term_plural": "",
        "reference": "",
        "comment": ""
    },
    {
        "term": "collection",
        "definition": null,
        "context": "\"pool\".\"category\"",
        "term_plural": "",
        "reference": "",
        "comment": ""
    },
    {
        "term": "hint",
        "definition": null,
        "context": "\"pool\".\"search\"",
        "term_plural": "",
        "reference": "",
        "comment": ""
    },
    {
        "term": "last_updated",
        "definition": null,
        "context": "\"pool\".\"detail\"",
        "term_plural": "",
        "reference": "",
        "comment": ""
    },
    {
        "term": "settings",
        "definition": null,
        "context": "\"settings\"",
        "term_plural": "",
        "reference": "",
        "comment": ""
    },
    {
        "term": "app_settings",
        "definition": null,
        "context": "\"settings\"",
        "term_plural": "",
        "reference": "",
        "comment": ""
    },
    {
        "term": "appearance",
        "definition": null,
        "context": "\"settings\"",
        "term_plural": "",
        "reference": "",
        "comment": ""
    },
    {
        "term": "general",
        "definition": null,
        "context": "\"settings\"",
        "term_plural": "",
        "reference": "",
        "comment": ""
    },
    {
        "term": "search",
        "definition": null,
        "context": "\"settings\"",
        "term_plural": "",
        "reference": "",
        "comment": ""
    },
    {
        "term": "information",
        "definition": null,
        "context": "\"settings\"",
        "term_plural": "",
        "reference": "",
        "comment": ""
    },
    {
        "term": "changelog",
        "definition": null,
        "context": "\"settings\"",
        "term_plural": "",
        "reference": "",
        "comment": ""
    },
    {
        "term": "general_data_source",
        "definition": null,
        "context": "\"settings\"",
        "term_plural": "",
        "reference": "",
        "comment": ""
    },
    {
        "term": "infinite_scroll_warning",
        "definition": null,
        "context": "\"settings\"",
        "term_plural": "",
        "reference": "",
        "comment": ""
    },
    {
        "term": "result_layout",
        "definition": null,
        "context": "\"settings\".\"result_layout\"",
        "term_plural": "",
        "reference": "",
        "comment": ""
    },
    {
        "term": "infinite_scroll",
        "definition": null,
        "context": "\"settings\".\"result_layout\"",
        "term_plural": "",
        "reference": "",
        "comment": ""
    },
    {
        "term": "pagination",
        "definition": null,
        "context": "\"settings\".\"result_layout\"",
        "term_plural": "",
        "reference": "",
        "comment": ""
    },
    {
        "term": "details_style",
        "definition": null,
        "context": "\"settings\".\"details_style\"",
        "term_plural": "",
        "reference": "",
        "comment": ""
    },
    {
        "term": "post_focused",
        "definition": null,
        "context": "\"settings\".\"details_style\"",
        "term_plural": "",
        "reference": "",
        "comment": ""
    },
    {
        "term": "image_focused",
        "definition": null,
        "context": "\"settings\".\"details_style\"",
        "term_plural": "",
        "reference": "",
        "comment": ""
    },
    {
        "term": "image_list",
        "definition": null,
        "context": "\"settings\".\"image_list\"",
        "term_plural": "",
        "reference": "",
        "comment": ""
    },
    {
        "term": "standard",
        "definition": null,
        "context": "\"settings\".\"image_list\"",
        "term_plural": "",
        "reference": "",
        "comment": ""
    },
    {
        "term": "masonry",
        "definition": null,
        "context": "\"settings\".\"image_list\"",
        "term_plural": "",
        "reference": "",
        "comment": ""
    },
    {
        "term": "image_grid",
        "definition": null,
        "context": "\"settings\".\"image_grid\"",
        "term_plural": "",
        "reference": "",
        "comment": ""
    },
    {
        "term": "grid_size",
        "definition": null,
        "context": "\"settings\".\"image_grid\".\"grid_size\"",
        "term_plural": "",
        "reference": "",
        "comment": ""
    },
    {
        "term": "small",
        "definition": null,
        "context": "\"settings\".\"image_grid\".\"grid_size\"",
        "term_plural": "",
        "reference": "",
        "comment": ""
    },
    {
        "term": "medium",
        "definition": null,
        "context": "\"settings\".\"image_grid\".\"grid_size\"",
        "term_plural": "",
        "reference": "",
        "comment": ""
    },
    {
        "term": "large",
        "definition": null,
        "context": "\"settings\".\"image_grid\".\"grid_size\"",
        "term_plural": "",
        "reference": "",
        "comment": ""
    },
    {
        "term": "image_quality",
        "definition": null,
        "context": "\"settings\".\"image_grid\".\"image_quality\"",
        "term_plural": "",
        "reference": "",
        "comment": ""
    },
    {
        "term": "high_quality_notice",
        "definition": null,
        "context": "\"settings\".\"image_grid\".\"image_quality\"",
        "term_plural": "",
        "reference": "",
        "comment": ""
    },
    {
        "term": "high",
        "definition": null,
        "context": "\"settings\".\"image_grid\".\"image_quality\"",
        "term_plural": "",
        "reference": "",
        "comment": ""
    },
    {
        "term": "low",
        "definition": null,
        "context": "\"settings\".\"image_grid\".\"image_quality\"",
        "term_plural": "",
        "reference": "",
        "comment": ""
    },
    {
        "term": "original",
        "definition": null,
        "context": "\"settings\".\"image_grid\".\"image_quality\"",
        "term_plural": "",
        "reference": "",
        "comment": ""
    },
    {
        "term": "automatic",
        "definition": null,
        "context": "\"settings\".\"image_grid\".\"image_quality\"",
        "term_plural": "",
        "reference": "",
        "comment": ""
    },
    {
        "term": "spacing",
        "definition": null,
        "context": "\"settings\".\"image_grid\"",
        "term_plural": "",
        "reference": "",
        "comment": ""
    },
    {
        "term": "corner_radius",
        "definition": null,
        "context": "\"settings\".\"image_grid\"",
        "term_plural": "",
        "reference": "",
        "comment": ""
    },
    {
        "term": "image_viewer",
        "definition": null,
        "context": "\"settings\".\"image_viewer\"",
        "term_plural": "",
        "reference": "",
        "comment": ""
    },
    {
        "term": "full_res_as_default",
        "definition": null,
        "context": "\"settings\".\"image_viewer\"",
        "term_plural": "",
        "reference": "",
        "comment": ""
    },
    {
        "term": "full_res_notice",
        "definition": null,
        "context": "\"settings\".\"image_viewer\"",
        "term_plural": "",
        "reference": "",
        "comment": ""
    },
    {
        "term": "image_detail",
        "definition": null,
        "context": "\"settings\".\"image_detail\"",
        "term_plural": "",
        "reference": "",
        "comment": ""
    },
    {
        "term": "language",
        "definition": null,
        "context": "\"settings\".\"language\"",
        "term_plural": "",
        "reference": "",
        "comment": ""
    },
    {
        "term": "english",
        "definition": null,
        "context": "\"settings\".\"language\"",
        "term_plural": "",
        "reference": "",
        "comment": ""
    },
    {
        "term": "russian",
        "definition": null,
        "context": "\"settings\".\"language\"",
        "term_plural": "",
        "reference": "",
        "comment": ""
    },
    {
        "term": "belarusian",
        "definition": null,
        "context": "\"settings\".\"language\"",
        "term_plural": "",
        "reference": "",
        "comment": ""
    },
    {
        "term": "vietnamese",
        "definition": null,
        "context": "\"settings\".\"language\"",
        "term_plural": "",
        "reference": "",
        "comment": ""
    },
    {
        "term": "japanese",
        "definition": null,
        "context": "\"settings\".\"language\"",
        "term_plural": "",
        "reference": "",
        "comment": ""
    },
    {
        "term": "german",
        "definition": null,
        "context": "\"settings\".\"language\"",
        "term_plural": "",
        "reference": "",
        "comment": ""
    },
    {
        "term": "theme",
        "definition": null,
        "context": "\"settings\".\"theme\"",
        "term_plural": "",
        "reference": "",
        "comment": ""
    },
    {
        "term": "dark",
        "definition": null,
        "context": "\"settings\".\"theme\"",
        "term_plural": "",
        "reference": "",
        "comment": ""
    },
    {
        "term": "light",
        "definition": null,
        "context": "\"settings\".\"theme\"",
        "term_plural": "",
        "reference": "",
        "comment": ""
    },
    {
        "term": "amoled_dark",
        "definition": null,
        "context": "\"settings\".\"theme\"",
        "term_plural": "",
        "reference": "",
        "comment": ""
    },
    {
        "term": "privacy",
        "definition": null,
        "context": "\"settings\".\"privacy\"",
        "term_plural": "",
        "reference": "",
        "comment": ""
    },
    {
        "term": "send_error_data_notice",
        "definition": null,
        "context": "\"settings\".\"privacy\"",
        "term_plural": "",
        "reference": "",
        "comment": ""
    },
    {
        "term": "performance",
        "definition": null,
        "context": "\"settings\".\"performance\"",
        "term_plural": "",
        "reference": "",
        "comment": ""
    },
    {
        "term": "posts_per_page",
        "definition": null,
        "context": "\"settings\".\"performance\"",
        "term_plural": "",
        "reference": "",
        "comment": ""
    },
    {
        "term": "posts_per_page_explain",
        "definition": null,
        "context": "\"settings\".\"performance\"",
        "term_plural": "",
        "reference": "",
        "comment": ""
    },
    {
        "term": "safe_mode",
        "definition": null,
        "context": "\"settings\"",
        "term_plural": "",
        "reference": "",
        "comment": ""
    },
    {
        "term": "remove",
        "definition": null,
        "context": "\"blacklisted_tags\"",
        "term_plural": "",
        "reference": "",
        "comment": ""
    },
    {
        "term": "edit",
        "definition": null,
        "context": "\"blacklisted_tags\"",
        "term_plural": "",
        "reference": "",
        "comment": ""
    },
    {
        "term": "blacklisted_tags",
        "definition": null,
        "context": "\"blacklisted_tags\"",
        "term_plural": "",
        "reference": "",
        "comment": ""
    },
    {
        "term": "load_error",
        "definition": null,
        "context": "\"blacklisted_tags\"",
        "term_plural": "",
        "reference": "",
        "comment": ""
    },
    {
        "term": "updated",
        "definition": null,
        "context": "\"blacklisted_tags\"",
        "term_plural": "",
        "reference": "",
        "comment": ""
    },
    {
        "term": "limitation_notice",
        "definition": null,
        "context": "\"blacklisted_tags\"",
        "term_plural": "",
        "reference": "",
        "comment": ""
    },
    {
        "term": "download",
        "definition": null,
        "context": "\"download\"",
        "term_plural": "",
        "reference": "",
        "comment": ""
    },
    {
        "term": "bulk_download",
        "definition": null,
        "context": "\"download\"",
        "term_plural": "",
        "reference": "",
        "comment": ""
    },
    {
        "term": "bulk_download_tag_confirmation",
        "definition": null,
        "context": "\"download\"",
        "term_plural": "",
        "reference": "",
        "comment": ""
    },
    {
        "term": "bulk_download_save_to_folder",
        "definition": null,
        "context": "\"download\"",
        "term_plural": "",
        "reference": "",
        "comment": ""
    },
    {
        "term": "bulk_download_total_count",
        "definition": null,
        "context": "\"download\"",
        "term_plural": "",
        "reference": "",
        "comment": ""
    },
    {
        "term": "bulk_download_done_count",
        "definition": null,
        "context": "\"download\"",
        "term_plural": "",
        "reference": "",
        "comment": ""
    },
    {
        "term": "bulk_download_done_confirm",
        "definition": null,
        "context": "\"download\"",
        "term_plural": "",
        "reference": "",
        "comment": ""
    },
    {
        "term": "bulk_download_cancel",
        "definition": null,
        "context": "\"download\"",
        "term_plural": "",
        "reference": "",
        "comment": ""
    },
    {
        "term": "bulk_download_duplicate",
        "definition": null,
        "context": "\"download\"",
        "term_plural": "",
        "reference": "",
        "comment": ""
    },
    {
        "term": "bulk_download_invalid_folder_name_error",
        "definition": null,
        "context": "\"download\"",
        "term_plural": "",
        "reference": "",
        "comment": ""
    },
    {
        "term": "bulk_download_only_download_new_images",
        "definition": null,
        "context": "\"download\"",
        "term_plural": "",
        "reference": "",
        "comment": ""
    },
    {
        "term": "bulk_download_stay_on_screen_request",
        "definition": null,
        "context": "\"download\"",
        "term_plural": "",
        "reference": "",
        "comment": ""
    },
    {
        "term": "bulk_download_folder_select_warning",
        "definition": null,
        "context": "\"download\"",
        "term_plural": "",
        "reference": "",
        "comment": ""
    },
    {
        "term": "bulk_download_select_a_folder",
        "definition": null,
        "context": "\"download\"",
        "term_plural": "",
        "reference": "",
        "comment": ""
    },
    {
        "term": "bulk_download_found_duplicate",
        "definition": null,
        "context": "\"download\"",
        "term_plural": "",
        "reference": "",
        "comment": ""
    },
    {
        "term": "bulk_download_downloaded_counter",
        "definition": {
            "other": ""
        },
        "context": "\"download\"",
        "term_plural": "bulk_download_downloaded_counter",
        "reference": "",
        "comment": ""
    },
    {
        "term": "bulk_download_skipped_counter",
        "definition": {
            "other": ""
        },
        "context": "\"download\"",
        "term_plural": "bulk_download_skipped_counter",
        "reference": "",
        "comment": ""
    },
    {
        "term": "bulk_download_download_more",
        "definition": null,
        "context": "\"download\"",
        "term_plural": "",
        "reference": "",
        "comment": ""
    },
    {
        "term": "open_app_settings",
        "definition": null,
        "context": "\"download\"",
        "term_plural": "",
        "reference": "",
        "comment": ""
    },
    {
        "term": "storage_permission_explanation",
        "definition": null,
        "context": "\"download\"",
        "term_plural": "",
        "reference": "",
        "comment": ""
    },
    {
        "term": "app_restart_request",
        "definition": null,
        "context": "\"download\"",
        "term_plural": "",
        "reference": "",
        "comment": ""
    },
    {
        "term": "image_counter",
        "definition": {
            "other": ""
        },
        "context": "\"download\"",
        "term_plural": "image_counter",
        "reference": "",
        "comment": ""
    },
    {
        "term": "saved_search",
        "definition": null,
        "context": "\"saved_search\"",
        "term_plural": "",
        "reference": "",
        "comment": ""
    },
    {
        "term": "saved_search_counter",
        "definition": {
            "other": ""
        },
        "context": "\"saved_search\"",
        "term_plural": "saved_search_counter",
        "reference": "",
        "comment": ""
    },
    {
        "term": "add_saved_search",
        "definition": null,
        "context": "\"saved_search\"",
        "term_plural": "",
        "reference": "",
        "comment": ""
    },
    {
        "term": "saved_search_added",
        "definition": null,
        "context": "\"saved_search\"",
        "term_plural": "",
        "reference": "",
        "comment": ""
    },
    {
        "term": "empty_saved_search",
        "definition": null,
        "context": "\"saved_search\"",
        "term_plural": "",
        "reference": "",
        "comment": ""
    },
    {
        "term": "update_saved_search",
        "definition": null,
        "context": "\"saved_search\"",
        "term_plural": "",
        "reference": "",
        "comment": ""
    },
    {
        "term": "saved_search_updated",
        "definition": null,
        "context": "\"saved_search\"",
        "term_plural": "",
        "reference": "",
        "comment": ""
    },
    {
        "term": "saved_search_feed",
        "definition": null,
        "context": "\"saved_search\"",
        "term_plural": "",
        "reference": "",
        "comment": ""
    },
    {
        "term": "saved_search_help",
        "definition": null,
        "context": "\"saved_search\"",
        "term_plural": "",
        "reference": "",
        "comment": ""
    },
    {
        "term": "saved_search_examples",
        "definition": null,
        "context": "\"saved_search\"",
        "term_plural": "",
        "reference": "",
        "comment": ""
    },
    {
        "term": "saved_search_try",
        "definition": null,
        "context": "\"saved_search\"",
        "term_plural": "",
        "reference": "",
        "comment": ""
    },
    {
        "term": "saved_search_query",
        "definition": null,
        "context": "\"saved_search\"",
        "term_plural": "",
        "reference": "",
        "comment": ""
    },
    {
        "term": "saved_search_labels",
        "definition": null,
        "context": "\"saved_search\"",
        "term_plural": "",
        "reference": "",
        "comment": ""
    },
    {
        "term": "saved_search_labels_description",
        "definition": null,
        "context": "\"saved_search\"",
        "term_plural": "",
        "reference": "",
        "comment": ""
    },
    {
        "term": "counter",
        "definition": {
            "other": ""
        },
        "context": "\"favorites\"",
        "term_plural": "counter",
        "reference": "",
        "comment": ""
    },
    {
        "term": "favorited",
        "definition": null,
        "context": "\"favorites\"",
        "term_plural": "",
        "reference": "",
        "comment": ""
    },
    {
        "term": "favorite",
        "definition": null,
        "context": "\"favorites\"",
        "term_plural": "",
        "reference": "",
        "comment": ""
    },
    {
        "term": "unfavorited",
        "definition": null,
        "context": "\"favorites\"",
        "term_plural": "",
        "reference": "",
        "comment": ""
    },
    {
        "term": "unfavorite",
        "definition": null,
        "context": "\"favorites\"",
        "term_plural": "",
        "reference": "",
        "comment": ""
    },
    {
        "term": "failed_to_unfavorite",
        "definition": null,
        "context": "\"favorites\"",
        "term_plural": "",
        "reference": "",
        "comment": ""
    },
    {
        "term": "failed_to_favorite",
        "definition": null,
        "context": "\"favorites\"",
        "term_plural": "",
        "reference": "",
        "comment": ""
    },
    {
        "term": "favorite_groups",
        "definition": null,
        "context": "\"favorite_groups\"",
        "term_plural": "",
        "reference": "",
        "comment": ""
    },
    {
        "term": "empty_group_notice",
        "definition": null,
        "context": "\"favorite_groups\"",
        "term_plural": "",
        "reference": "",
        "comment": ""
    },
    {
        "term": "create_group",
        "definition": null,
        "context": "\"favorite_groups\"",
        "term_plural": "",
        "reference": "",
        "comment": ""
    },
    {
        "term": "edit_group",
        "definition": null,
        "context": "\"favorite_groups\"",
        "term_plural": "",
        "reference": "",
        "comment": ""
    },
    {
        "term": "add_to_group_dialog_title",
        "definition": null,
        "context": "\"favorite_groups\"",
        "term_plural": "",
        "reference": "",
        "comment": ""
    },
    {
        "term": "add_to",
        "definition": null,
        "context": "\"favorite_groups\"",
        "term_plural": "",
        "reference": "",
        "comment": ""
    },
    {
        "term": "create",
        "definition": null,
        "context": "\"favorite_groups\"",
        "term_plural": "",
        "reference": "",
        "comment": ""
    },
    {
        "term": "private",
        "definition": null,
        "context": "\"favorite_groups\"",
        "term_plural": "",
        "reference": "",
        "comment": ""
    },
    {
        "term": "view_more_popup",
        "definition": null,
        "context": "\"favorite_groups\"",
        "term_plural": "",
        "reference": "",
        "comment": ""
    },
    {
        "term": "items_added_notification_popup",
        "definition": null,
        "context": "\"favorite_groups\"",
        "term_plural": "",
        "reference": "",
        "comment": ""
    },
    {
        "term": "group_name",
        "definition": null,
        "context": "\"favorite_groups\"",
        "term_plural": "",
        "reference": "",
        "comment": ""
    },
    {
        "term": "group_name_hint",
        "definition": null,
        "context": "\"favorite_groups\"",
        "term_plural": "",
        "reference": "",
        "comment": ""
    },
    {
        "term": "all_posts",
        "definition": null,
        "context": "\"favorite_groups\"",
        "term_plural": "",
        "reference": "",
        "comment": ""
    },
    {
        "term": "initial_posts_hint",
        "definition": null,
        "context": "\"favorite_groups\"",
        "term_plural": "",
        "reference": "",
        "comment": ""
    },
    {
        "term": "is_private_group_option",
        "definition": null,
        "context": "\"favorite_groups\"",
        "term_plural": "",
        "reference": "",
        "comment": ""
    },
    {
        "term": "create_group_cancel",
        "definition": null,
        "context": "\"favorite_groups\"",
        "term_plural": "",
        "reference": "",
        "comment": ""
    },
    {
        "term": "create_group_confirm",
        "definition": null,
        "context": "\"favorite_groups\"",
        "term_plural": "",
        "reference": "",
        "comment": ""
    },
    {
        "term": "max_limit_warning",
        "definition": null,
        "context": "\"favorite_groups\"",
        "term_plural": "",
        "reference": "",
        "comment": ""
    },
    {
        "term": "duplicate_items_warning_notification",
        "definition": null,
        "context": "\"favorite_groups\"",
        "term_plural": "",
        "reference": "",
        "comment": ""
    },
    {
        "term": "detete_confirmation",
        "definition": null,
        "context": "\"favorite_groups\"",
        "term_plural": "",
        "reference": "",
        "comment": ""
    },
    {
        "term": "group_item_counter",
        "definition": {
            "other": ""
        },
        "context": "\"favorite_groups\"",
        "term_plural": "group_item_counter",
        "reference": "",
        "comment": ""
    },
    {
        "term": "favorites",
        "definition": null,
        "context": "\"favorite_tags\"",
        "term_plural": "",
        "reference": "",
        "comment": ""
    },
    {
        "term": "or",
        "definition": null,
        "context": "\"favorite_tags\"",
        "term_plural": "",
        "reference": "",
        "comment": ""
    },
    {
        "term": "import",
        "definition": null,
        "context": "\"favorite_tags\"",
        "term_plural": "",
        "reference": "",
        "comment": ""
    },
    {
        "term": "import_hint",
        "definition": null,
        "context": "\"favorite_tags\"",
        "term_plural": "",
        "reference": "",
        "comment": ""
    },
    {
        "term": "cancel",
        "definition": null,
        "context": "\"favorite_tags\"",
        "term_plural": "",
        "reference": "",
        "comment": ""
    },
    {
        "term": "export",
        "definition": null,
        "context": "\"favorite_tags\"",
        "term_plural": "",
        "reference": "",
        "comment": ""
    },
    {
        "term": "export_notification",
        "definition": null,
        "context": "\"favorite_tags\"",
        "term_plural": "",
        "reference": "",
        "comment": ""
    },
    {
        "term": "rate_request",
        "definition": null,
        "context": "\"rating\"",
        "term_plural": "",
        "reference": "",
        "comment": ""
    },
    {
        "term": "rate",
        "definition": null,
        "context": "\"rating\"",
        "term_plural": "",
        "reference": "",
        "comment": ""
    },
    {
        "term": "cancel",
        "definition": null,
        "context": "\"rating\"",
        "term_plural": "",
        "reference": "",
        "comment": ""
    },
    {
        "term": "later",
        "definition": null,
        "context": "\"rating\"",
        "term_plural": "",
        "reference": "",
        "comment": ""
    },
    {
        "term": "rationale",
        "definition": null,
        "context": "\"rating\"",
        "term_plural": "",
        "reference": "",
        "comment": ""
    },
    {
        "term": "login",
        "definition": null,
        "context": "\"sideMenu\"",
        "term_plural": "",
        "reference": "",
        "comment": ""
    },
    {
        "term": "profile",
        "definition": null,
        "context": "\"sideMenu\"",
        "term_plural": "",
        "reference": "",
        "comment": ""
    },
    {
        "term": "settings",
        "definition": null,
        "context": "\"sideMenu\"",
        "term_plural": "",
        "reference": "",
        "comment": ""
    },
    {
        "term": "day",
        "definition": null,
        "context": "\"dateRange\"",
        "term_plural": "",
        "reference": "",
        "comment": ""
    },
    {
        "term": "week",
        "definition": null,
        "context": "\"dateRange\"",
        "term_plural": "",
        "reference": "",
        "comment": ""
    },
    {
        "term": "month",
        "definition": null,
        "context": "\"dateRange\"",
        "term_plural": "",
        "reference": "",
        "comment": ""
    }
]